selenium_package/actions/__init__.py
selenium_package/actions/click_on_element.py
selenium_package/actions/click_on_the_screen.py
selenium_package/actions/close_all_tabs_except_that_contains_title.py
selenium_package/actions/close_all_tabs_except_that_has_title.py
selenium_package/actions/go_back_to_the_previous_page.py
selenium_package/actions/go_to_tab_that_contains_title.py
selenium_package/actions/go_to_tab_that_contains_url.py
selenium_package/actions/go_to_tab_that_has_title.py
selenium_package/actions/insert_text.py
selenium_package/actions/redirect_to_page.py
selenium_package/executors/__init__.py
selenium_package/executors/default_executor.py
selenium_package/executors/retry_action_by_max_attempts.py
selenium_package/executors/retry_action_until_another_tab_is_opened.py
selenium_package/executors/retry_action_until_element_contains_a_property_value.py
selenium_package/executors/retry_action_until_element_has_a_property_value.py
selenium_package/executors/retry_action_until_element_is_located.py
selenium_package/executors/retry_action_until_new_file_has_been_detected.py
selenium_package/executors/retry_action_until_number_of_tabs_is.py
selenium_package/executors/retry_action_until_page_title_contains.py
selenium_package/executors/retry_action_until_page_title_is.py
selenium_package/executors/retry_action_until_url_contains.py
selenium_package/executors/retry_executor.py
selenium_package/executors/retry_insert_text_until_value_is_correct.py
selenium_package/executors/timeout_executor.py
selenium_package/interfaces/__init__.py
selenium_package/interfaces/base_action.py
selenium_package/interfaces/base_executor.py
selenium_package/interfaces/exceptions/__init__.py
selenium_package/interfaces/exceptions/exceptions.py
selenium_package/utils/__init__.py
selenium_package/utils/file_service/__init__.py
selenium_package/utils/file_service/functions.py
selenium_package/utils/messages/__init__.py
selenium_package/utils/messages/messages.py
selenium_package-0.0.1.dist-info/METADATA
selenium_package-0.0.1.dist-info/WHEEL
selenium_package-0.0.1.dist-info/licenses/LICENSE
selenium_package-0.0.1.dist-info/RECORD
