Metadata-Version: 2.4
Name: selenium_package
Version: 0.0.1
Summary: A Python package for Selenium automation with action and executor patterns.
Project-URL: Homepage, https://github.com/jgabrielsb-sb/selenium-package
Project-URL: Issues, https://github.com/jgabrielsb-sb/selenium-package/issues
Author-email: João Gabriel Sampaio de Barros <jgabrielsb2002@gmail.com>
License-Expression: MIT
License-File: LICENSE
Classifier: Operating System :: OS Independent
Classifier: Programming Language :: Python :: 3
Requires-Python: >=3.9
Requires-Dist: pytest>=8.4.2
Requires-Dist: selenium>=4.36.0
Requires-Dist: sphinx>=7.4.7
Provides-Extra: dev
Requires-Dist: black>=23.0.0; extra == 'dev'
Requires-Dist: isort>=5.12.0; extra == 'dev'
Requires-Dist: mypy>=1.0.0; extra == 'dev'
Requires-Dist: pytest-cov>=4.0.0; extra == 'dev'
Requires-Dist: pytest>=7.4.0; extra == 'dev'
